q2/__init__.py
q2/tool.py
q2/agents/__init__.py
q2/agents/__main__.py
q2/agents/agent.py
q2/agents/history.py
q2/agents/noise.py
q2/agents/random.py
q2/agents/utils.py
q2/agents/deep_q/__init__.py
q2/agents/deep_q/deep_q_agent.py
q2/agents/deep_q/q_net.py
q2/agents/supervised/__init__.py
q2/agents/supervised/supervised_agent.py
q2/config/__init__.py
q2/environments/__init__.py
q2/environments/__main__.py
q2/environments/environment.py
q2/environments/maker.py
q2/generate/__init__.py
q2/generate/__main__.py
q2/generate/templates/agent.py
q2/generate/templates/environment.py
q2/generate/templates/objective.py
q2/generate/templates/regimen.py
q2/objectives/__init__.py
q2/objectives/objective.py
q2/objectives/passthrough.py
q2/regimens/__init__.py
q2/regimens/__main__.py
q2/regimens/offline.py
q2/regimens/online.py
q2/regimens/plugin.py
q2/regimens/regimen.py
q2/regimens/rl2.py
q2/regimens/plugins/__init__.py
q2/regimens/plugins/display_framerate.py
q2/regimens/plugins/manual_override.py
q2/regimens/plugins/no_progress_early_stopping.py
q2/regimens/plugins/save_training_data.py
q2/train/__init__.py
q2/train/__main__.py
q2/train/data.py
q2/train/utils.py
q2-0.1.4.dist-info/METADATA
q2-0.1.4.dist-info/RECORD
q2-0.1.4.dist-info/WHEEL
q2-0.1.4.dist-info/entry_points.txt
q2-0.1.4.dist-info/top_level.txt
