Metadata-Version: 2.1
Name: q2
Version: 0.1.4
Summary: A reinforcement learning framework and command line tool
Home-page: https://github.com/tdb-alcorn/q2
Author: Tom Alcorn
Author-email: tdb.alcorn@gmail.com
License: MIT
Keywords: deep reinforcement learning framework tool
Platform: UNKNOWN
Classifier: Development Status :: 3 - Alpha
Classifier: License :: OSI Approved :: MIT License
Classifier: Programming Language :: Python :: 3.5
Classifier: Programming Language :: Python :: 3.6
Classifier: Programming Language :: Python :: 3.7
Classifier: Environment :: Console
Classifier: Topic :: Scientific/Engineering :: Artificial Intelligence
Classifier: Topic :: Scientific/Engineering :: Artificial Life
Requires-Dist: numpy
Requires-Dist: tensorflow
Requires-Dist: PyYAML
Requires-Dist: gym
Requires-Dist: gym-retro
